MANIFEST.in
setup.cfg
setup.py
thulac_test/__init__.py
thulac_test/__main__.py
thulac_test/text.txt
thulac_test.egg-info/PKG-INFO
thulac_test.egg-info/SOURCES.txt
thulac_test.egg-info/dependency_links.txt
thulac_test.egg-info/top_level.txt
thulac_test/base/AlphaBeta.py
thulac_test/base/Dat.py
thulac_test/base/Node.py
thulac_test/base/WordWithTag.py
thulac_test/base/__init__.py
thulac_test/base/compatibility.py
thulac_test/character/CBModel.py
thulac_test/character/CBNGramFeature.py
thulac_test/character/CBTaggingDecoder.py
thulac_test/character/__init__.py
thulac_test/manage/Filter.py
thulac_test/manage/Postprocesser.py
thulac_test/manage/Preprocesser.py
thulac_test/manage/Punctuation.py
thulac_test/manage/TimeWord.py
thulac_test/manage/__init__.py
thulac_test/manage/verbword.py
thulac_test/models/__init__.py
thulac_test/models/cws_dat.bin
thulac_test/models/cws_label.txt
thulac_test/models/cws_model.bin
thulac_test/models/idiom.dat
thulac_test/models/model_c_dat.bin
thulac_test/models/model_c_label.txt
thulac_test/models/model_c_model.bin
thulac_test/models/model_w
thulac_test/models/neg.dat
thulac_test/models/ns.dat
thulac_test/models/singlepun.dat
thulac_test/models/t2s.dat
thulac_test/models/time.dat
thulac_test/models/vD.dat
thulac_test/models/vM.dat
thulac_test/models/xu.dat