Metadata-Version: 1.1
Name: thulac-test
Version: 0.9.5
Summary: A random test lib
Home-page: https://github.com/thunlp/THULAC-Python
Author: Peter Downs
Author-email: majunhua133256@gmail.com
License: UNKNOWN
Download-URL: https://github.com/thunlp/THULAC-Python/archive/master.zip
Keywords: testing,logging,example
Platform: UNKNOWN
